LICENSE
MANIFEST.in
README.md
setup.cfg
setup.py
django_signal_disabler.egg-info/PKG-INFO
django_signal_disabler.egg-info/SOURCES.txt
django_signal_disabler.egg-info/dependency_links.txt
django_signal_disabler.egg-info/not-zip-safe
django_signal_disabler.egg-info/requires.txt
django_signal_disabler.egg-info/top_level.txt
signal_disabler/__init__.py
signal_disabler/signal_disabler.py
tests/__init__.py
tests/conftest.py
tests/models.py
tests/test_configuration.py
tests/test_contextmanager.py
tests/test_decorator.py
tests/test_function.py
tests/urls.py