Metadata-Version: 1.0
Name: django-signal-disabler
Version: 0.1.1
Summary: Allows to temporarily disable django signals
Home-page: https://github.com/RobertKolner/django-signal-disabler
Author: Robert Kolner
Author-email: robert.kolner@gmail.com
License: MIT
Keywords: django,django-signals
Platform: UNKNOWN
